pyboplate/main.py
pyboplate-0.1.1.dist-info/METADATA
pyboplate-0.1.1.dist-info/WHEEL
pyboplate-0.1.1.dist-info/licenses/LICENSE
pyboplate-0.1.1.dist-info/RECORD
