Metadata-Version: 2.4
Name: pyboplate
Version: 0.1.1
Summary: A modern Python project template using uv for package management
Author-email: remixonwin <remixonwin@gmail.com>
License: MIT
License-File: LICENSE
Classifier: Development Status :: 3 - Alpha
Classifier: Intended Audience :: Developers
Classifier: License :: OSI Approved :: MIT License
Classifier: Programming Language :: Python :: 3
Classifier: Programming Language :: Python :: 3.8
Classifier: Programming Language :: Python :: 3.9
Classifier: Programming Language :: Python :: 3.10
Classifier: Programming Language :: Python :: 3.11
Classifier: Programming Language :: Python :: 3.12
Requires-Python: >=3.8
Requires-Dist: jsonschema
Requires-Dist: pytest-cov>=4.1.0
Requires-Dist: pyyaml
Requires-Dist: toml
